mailanalysis/__init__.py
mailanalysis/__main__.py
mailanalysis/processors/__init__.py
mailanalysis/processors/activity_over_time.py
mailanalysis/processors/dow_hour_heatmap.py
mailanalysis/processors/most_frequent_addresses.py
mailanalysis/static_assets/html_footer.html
mailanalysis/static_assets/html_header.html
mailbox_report_generator-0.1.3.dist-info/entry_points.txt
mailbox_report_generator-0.1.3.dist-info/WHEEL
mailbox_report_generator-0.1.3.dist-info/METADATA
mailbox_report_generator-0.1.3.dist-info/licenses/LICENSE
mailbox_report_generator-0.1.3.dist-info/RECORD
