Metadata-Version: 2.1
Name: mailbox_report_generator
Version: 0.1.3
Summary: Tool to analyze a mbox mail dump
License: MIT
Author-email: Jacopo Farina <jacopo1.farina@gmail.com>
Requires-Python: >=3.10
Requires-Dist: plotly==5.13.0
Requires-Dist: tqdm>=4.64.1
Project-URL: Bug Tracker, https://github.com/jacopofar/mailbox-report-generator/issues
Project-URL: Homepage, https://github.com/jacopofar/mailbox-report-generator
